highpymath-0.1.2.dist-info/METADATA
highpymath-0.1.2.dist-info/WHEEL
highpymath-0.1.2.dist-info/license_files/LICENSE
highpymath/__init__.py
highpymath/highpymath.cpython-312-arm-linux-gnueabihf.so
highpymath-0.1.2.dist-info/RECORD
