Metadata-Version: 2.3
Name: highpymath
Version: 0.1.2
Classifier: Programming Language :: Rust
Classifier: Programming Language :: Python :: Implementation :: CPython
Classifier: Programming Language :: Python :: Implementation :: PyPy
License-File: LICENSE
Summary: High Quality Math library for Python
Author-email: pyrootcpp <pyrootcpp@outlook.de>
License: MIT
Requires-Python: >=3.8
